fastPSO/__init__.py
fastPSO/pso.py
test/__init__.py
test/test_pso.py
fastPSO-0.0.2.dist-info/LICENSE
fastPSO-0.0.2.dist-info/METADATA
fastPSO-0.0.2.dist-info/WHEEL
fastPSO-0.0.2.dist-info/top_level.txt
fastPSO-0.0.2.dist-info/RECORD
