Metadata-Version: 2.1
Name: fastPSO
Version: 0.0.2
Summary: Fast parallel PSO library for Python with support for CPU and GPU multithreading.
Home-page: https://github.com/pribalta/fastPSO
Author: Pablo Ribalta Lorenzo
Author-email: pribalta@ieee.org
License: LICENSE.txt
Platform: UNKNOWN
Classifier: Programming Language :: Python :: 3
Classifier: License :: OSI Approved :: MIT License
Classifier: Operating System :: OS Independent
